odoo/addons/commission_settlement_line_percentage/README.rst
odoo/addons/commission_settlement_line_percentage/__init__.py
odoo/addons/commission_settlement_line_percentage/__manifest__.py
odoo/addons/commission_settlement_line_percentage/i18n/es.po
odoo/addons/commission_settlement_line_percentage/models/__init__.py
odoo/addons/commission_settlement_line_percentage/models/commission_settlement_line.py
odoo/addons/commission_settlement_line_percentage/report/report_settlement_document.xml
odoo/addons/commission_settlement_line_percentage/static/description/icon.png
odoo/addons/commission_settlement_line_percentage/views/commission.settlement_view.xml
odoo_addon_commission_settlement_line_percentage-15.0.1.0.0.2.dist-info/METADATA
odoo_addon_commission_settlement_line_percentage-15.0.1.0.0.2.dist-info/WHEEL
odoo_addon_commission_settlement_line_percentage-15.0.1.0.0.2.dist-info/top_level.txt
odoo_addon_commission_settlement_line_percentage-15.0.1.0.0.2.dist-info/RECORD
